datapusher/__init__.py
datapusher/jobs.py
datapusher/main.py
datapusher-0.0.15.dist-info/LICENSE
datapusher-0.0.15.dist-info/METADATA
datapusher-0.0.15.dist-info/WHEEL
datapusher-0.0.15.dist-info/entry_points.txt
datapusher-0.0.15.dist-info/top_level.txt
datapusher-0.0.15.dist-info/RECORD
