Metadata-Version: 2.1
Name: datapusher
Version: 0.0.15
Summary: A standalone web service that parses the contents of a CKAN site's data files and pushes them into its DataStore
Home-page: https://github.com/ckan/datapusher
Author: UNKNOWN
Author-email: UNKNOWN
License: AGPL
Keywords: ckan csv xls excel
Platform: UNKNOWN
Classifier: Development Status :: 4 - Beta
Classifier: License :: OSI Approved :: GNU Affero General Public License v3 or later (AGPLv3+)
Classifier: Programming Language :: Python :: 2.7
